tlz/__init__.py
tlz/_build_tlz.py
toolz/__init__.py
toolz/_signatures.py
toolz/_version.py
toolz/compatibility.py
toolz/dicttoolz.py
toolz/functoolz.py
toolz/itertoolz.py
toolz/recipes.py
toolz/utils.py
toolz/curried/__init__.py
toolz/curried/exceptions.py
toolz/curried/operator.py
toolz/sandbox/__init__.py
toolz/sandbox/core.py
toolz/sandbox/parallel.py
toolz/tests/test_compatibility.py
toolz/tests/test_curried.py
toolz/tests/test_curried_doctests.py
toolz/tests/test_dicttoolz.py
toolz/tests/test_functoolz.py
toolz/tests/test_inspect_args.py
toolz/tests/test_itertoolz.py
toolz/tests/test_recipes.py
toolz/tests/test_serialization.py
toolz/tests/test_signatures.py
toolz/tests/test_tlz.py
toolz/tests/test_utils.py
toolz-0.12.1.dist-info/AUTHORS.md
toolz-0.12.1.dist-info/LICENSE.txt
toolz-0.12.1.dist-info/METADATA
toolz-0.12.1.dist-info/WHEEL
toolz-0.12.1.dist-info/top_level.txt
toolz-0.12.1.dist-info/RECORD
