Metadata-Version: 1.2
Name: toolz
Version: 0.12.1
Summary: List processing tools and functional utilities
Home-page: https://github.com/pytoolz/toolz/
Author: https://raw.github.com/pytoolz/toolz/master/AUTHORS.md
Maintainer: Erik Welch
Maintainer-email: erik.n.welch@gmail.com
License: BSD
Keywords: functional utility itertools functools
Platform: UNKNOWN
Classifier: Development Status :: 5 - Production/Stable
Classifier: License :: OSI Approved :: BSD License
Classifier: Programming Language :: Python
Classifier: Programming Language :: Python :: 3
Classifier: Programming Language :: Python :: 3.7
Classifier: Programming Language :: Python :: 3.8
Classifier: Programming Language :: Python :: 3.9
Classifier: Programming Language :: Python :: 3.10
Classifier: Programming Language :: Python :: 3.11
Classifier: Programming Language :: Python :: 3.12
Classifier: Programming Language :: Python :: Implementation :: CPython
Classifier: Programming Language :: Python :: Implementation :: PyPy
Requires-Python: >=3.7
